README.md
setup.py
data_loader/__init__.py
data_loader/v1_data.py
data_loader/v2_data.py
deploy/__init__.py
model/__init__.py
model/convert.py
model/ernie.py
model/onnx_helper.py
model/turbo_match.py
ptmchat.egg-info/PKG-INFO
ptmchat.egg-info/SOURCES.txt
ptmchat.egg-info/dependency_links.txt
ptmchat.egg-info/entry_points.txt
ptmchat.egg-info/requires.txt
ptmchat.egg-info/top_level.txt
rank/__init__.py
rank/ranker.py
recall/__init__.py
recall/es_search.py
recall/semantic_search.py
running/__init__.py
running/chat.py
running/online_onnx.py
running/run.py
running/run_onnx.py
running/run_trt.py
running/run_turbo.py