Metadata-Version: 2.1
Name: ptmchat
Version: 0.0.1
Summary: pretrained ernie model based retrieval open domain chatting
Home-page: http://10.18.203.116/dialog/python-aispeech-ptmchat-api
Author: hisense
License: Apache License 2.0
Platform: UNKNOWN
